[
      {"day": "2015-11-01", "time": "17:25", "candy": "Heath"},
      {"day": "2015-11-01", "time": "17:27", "candy": "Kitkat"},
      {"day": "2015-11-01", "time": "17:38", "candy": "Whoppers"},
      {"day": "2015-11-01", "time": "17:38", "candy": "Whoppers"},
      {"day": "2015-11-02", "time": "17:02", "candy": "Twix"},
      {"day": "2015-11-02", "time": "17:03", "candy": "PBcup"},
      {"day": "2015-11-02", "time": "17:05", "candy": "PeanutMM"},
      {"day": "2015-11-02", "time": "18:10", "candy": "PBcup"},
      {"day": "2015-11-02", "time": "18:11", "candy": "AlmondJoy"},
      {"day": "2015-11-03", "time": "10:13", "candy": "PBcup"},
      {"day": "2015-11-03", "time": "10:13", "candy": "Pieces"},
      {"day": "2015-11-03", "time": "11:08", "candy": "PeanutMM"},
      {"day": "2015-11-03", "time": "11:19", "candy": "PBcup"},
      {"day": "2015-11-03", "time": "11:25", "candy": "PBcup"},
      {"day": "2015-11-03", "time": "15:27", "candy": "PBcup"},
      {"day": "2015-11-03", "time": "16:36", "candy": "Snickers"},
      {"day": "2015-11-03", "time": "19:22", "candy": "Twix"},
      {"day": "2015-11-03", "time": "19:22", "candy": "Twix"},
      {"day": "2015-11-04", "time": "16:50", "candy": "PBcup"},
      {"day": "2015-11-04", "time": "17:00", "candy": "MM"},
      {"day": "2015-11-05", "time": "12:20", "candy": "MM"},
      {"day": "2015-11-05", "time": "12:20", "candy": "MM"},
      {"day": "2015-11-05", "time": "12:20", "candy": "PBcup"},
      {"day": "2015-11-05", "time": "16:50", "candy": "Snickers"},
      {"day": "2015-11-05", "time": "17:00", "candy": "Snickers"},
      {"day": "2015-11-05", "time": "18:20", "candy": "Twix"},
      {"day": "2015-11-06", "time": "11:00", "candy": "Snickers"},
      {"day": "2015-11-06", "time": "13:20", "candy": "Snickers"},
      {"day": "2015-11-06", "time": "13:30", "candy": "Snickers"},
      {"day": "2015-11-06", "time": "14:30", "candy": "Pieces"},
      {"day": "2015-11-06", "time": "15:20", "candy": "Snickers"},
      {"day": "2015-11-07", "time": "15:10", "candy": "PBcup"},
      {"day": "2015-11-07", "time": "15:10", "candy": "PBcup"},
      {"day": "2015-11-07", "time": "16:00", "candy": "PeanutMM"}
]
